voiceinvoiceout/__init__.py
voiceinvoiceout/voiceinvoiceout_code.py
voiceinvoiceout-0.0.1.dist-info/LICENSE.txt
voiceinvoiceout-0.0.1.dist-info/METADATA
voiceinvoiceout-0.0.1.dist-info/WHEEL
voiceinvoiceout-0.0.1.dist-info/top_level.txt
voiceinvoiceout-0.0.1.dist-info/RECORD
