Metadata-Version: 2.1
Name: voiceinvoiceout
Version: 0.0.1
Summary: A module which helps you take voice input, voice output and many more...
Author: Vedant Barhate
Author-email: vedant.barhate27@gmail.com
Keywords: python,speech,speech-recognition,voice,audio,speak,sprint,text to speech,speech to text
Classifier: Development Status :: 1 - Planning
Classifier: Intended Audience :: Developers
Classifier: Programming Language :: Python :: 3
Classifier: Operating System :: Unix
Classifier: Operating System :: MacOS :: MacOS X
Classifier: Operating System :: Microsoft :: Windows
Classifier: License :: OSI Approved :: MIT License
License-File: LICENSE.txt
Requires-Dist: speechRecognition
Requires-Dist: pyttsx3
